{
  "submissions": [
    {
      "id": "SUB-1772122026725-dk4p2zlt5",
      "submittedBy": {
        "agentName": "TIMOTHY KIBUKUNA",
        "agentScCode": "05544657",
        "agentId": "1772033414438"
      },
      "clientInfo": {
        "fullName": "WETAKA MARGARET",
        "phoneNumber": "0776598436",
        "email": "m28012282@gmail.com",
        "nationalId": "CF80051104G49G",
        "dob": "1980-10-12",
        "gender": "female",
        "businessAddress": "North road",
        "residentialAddress": "Mbale",
        "nextOfKinName": "Kanyerere maria",
        "nextOfKinRelationship": "business_partner",
        "nextOfKinPhone": "0793138031"
      },
      "images": {
        "idFrontUrl": "https://raw.githubusercontent.com/BarasaGodwilTech/Ezee-money/main/images/submissions/SUB-1772122026725-dk4p2zlt5/idFront_1772122026769.jpg",
        "idBackUrl": "https://raw.githubusercontent.com/BarasaGodwilTech/Ezee-money/main/images/submissions/SUB-1772122026725-dk4p2zlt5/idBack_1772122049641.jpg",
        "agentPhotoUrl": "https://raw.githubusercontent.com/BarasaGodwilTech/Ezee-money/main/images/submissions/SUB-1772122026725-dk4p2zlt5/agentPhoto_1772122069178.jpg"
      },
      "submissionDate": "2026-02-26T16:08:07.054Z",
      "status": "pending"
    },
    {
      "id": "SUB-1772355923448-r3y6h7dpk",
      "submittedBy": {
        "agentName": "TIMOTHY KIBUKUNA",
        "agentScCode": "05544657",
        "agentId": "1772033414438"
      },
      "clientInfo": {
        "fullName": "Mukaaya Moses Tenywa",
        "phoneNumber": "0708258404",
        "email": "mosesmukaaya134@gmail.com",
        "nationalId": "CM95083103103C",
        "dob": "1995-10-05",
        "gender": "male",
        "businessAddress": "Napoli",
        "residentialAddress": "Mbale",
        "nextOfKinName": "Musubi cathy",
        "nextOfKinRelationship": "spouse",
        "nextOfKinPhone": "0757458404"
      },
      "images": {
        "idFrontUrl": "https://raw.githubusercontent.com/BarasaGodwilTech/Ezee-money/main/images/submissions/SUB-1772355923448-r3y6h7dpk/idFront_1772355923501.jpg",
        "idBackUrl": "https://raw.githubusercontent.com/BarasaGodwilTech/Ezee-money/main/images/submissions/SUB-1772355923448-r3y6h7dpk/idBack_1772355964594.jpg",
        "agentPhotoUrl": "https://raw.githubusercontent.com/BarasaGodwilTech/Ezee-money/main/images/submissions/SUB-1772355923448-r3y6h7dpk/agentPhoto_1772355995588.jpg"
      },
      "submissionDate": "2026-03-01T09:06:57.909Z",
      "status": "pending"
    },
    {
      "id": "SUB-1772723407964-bhbll4zf5",
      "submittedBy": {
        "agentName": "TIMOTHY KIBUKUNA",
        "agentScCode": "05544657",
        "agentId": "1772033414438"
      },
      "clientInfo": {
        "fullName": "OWORI INNOCENT",
        "phoneNumber": "0702207363",
        "email": "oworiinnocent2018@gmail.com",
        "nationalId": "CM9903910DCACD",
        "dob": "1999-06-05",
        "gender": "male",
        "businessAddress": "North road",
        "residentialAddress": "Mbale",
        "nextOfKinName": "Oketcho Andrew",
        "nextOfKinRelationship": "friend",
        "nextOfKinPhone": "0706018025"
      },
      "images": {
        "idFrontUrl": "https://raw.githubusercontent.com/BarasaGodwilTech/Ezee-money/main/images/submissions/SUB-1772723407964-bhbll4zf5/idFront_1772723408014.jpg",
        "idBackUrl": "https://raw.githubusercontent.com/BarasaGodwilTech/Ezee-money/main/images/submissions/SUB-1772723407964-bhbll4zf5/idBack_1772723427737.jpg",
        "agentPhotoUrl": "https://raw.githubusercontent.com/BarasaGodwilTech/Ezee-money/main/images/submissions/SUB-1772723407964-bhbll4zf5/agentPhoto_1772723446717.jpg"
      },
      "submissionDate": "2026-03-05T15:10:59.362Z",
      "status": "pending"
    },
    {
      "id": "SUB-1772898362526-cfxdopy49",
      "submittedBy": {
        "agentName": "TIMOTHY KIBUKUNA",
        "agentScCode": "05544657",
        "agentId": "1772033414438"
      },
      "clientInfo": {
        "fullName": "NAMUKONGO FRANCIS",
        "phoneNumber": "0753852313",
        "email": "namukongofrancis20@gmail.com",
        "nationalId": "CM97067105QHUH",
        "dob": "1997-10-03",
        "gender": "male",
        "businessAddress": "Nauyo",
        "residentialAddress": "Mbale",
        "nextOfKinName": "Namono Flavia",
        "nextOfKinRelationship": "sibling",
        "nextOfKinPhone": "0757689646"
      },
      "images": {
        "idFrontUrl": "https://raw.githubusercontent.com/BarasaGodwilTech/Ezee-money/main/images/submissions/SUB-1772898362526-cfxdopy49/idFront_1772898362565.jpg",
        "idBackUrl": "https://raw.githubusercontent.com/BarasaGodwilTech/Ezee-money/main/images/submissions/SUB-1772898362526-cfxdopy49/idBack_1772898379042.jpg",
        "agentPhotoUrl": "https://raw.githubusercontent.com/BarasaGodwilTech/Ezee-money/main/images/submissions/SUB-1772898362526-cfxdopy49/agentPhoto_1772898388170.jpg"
      },
      "submissionDate": "2026-03-07T15:46:39.030Z",
      "status": "pending"
    },
    {
      "id": "SUB-1773074150582-bw0b0cb1h",
      "submittedBy": {
        "agentName": "Barasa Godwill",
        "agentScCode": "SC001",
        "agentId": "1771597985946"
      },
      "clientInfo": {
        "fullName": "g",
        "phoneNumber": "537838",
        "email": "barasagodwil@livingstone.ac.ug",
        "nationalId": "sfjsfgjjsfh",
        "dob": "2026-03-14",
        "gender": "female",
        "businessAddress": "shfjsj",
        "residentialAddress": "sfhjsfj",
        "nextOfKinName": "fhjsfjh",
        "nextOfKinRelationship": "parent",
        "nextOfKinPhone": "46772"
      },
      "images": {
        "idFrontUrl": "https://raw.githubusercontent.com/BarasaGodwilTech/Ezee-money/main/images/submissions/SUB-1773074150582-bw0b0cb1h/idFront_1773074150586.jpg",
        "idBackUrl": "https://raw.githubusercontent.com/BarasaGodwilTech/Ezee-money/main/images/submissions/SUB-1773074150582-bw0b0cb1h/idBack_1773074154276.jpg",
        "agentPhotoUrl": "https://raw.githubusercontent.com/BarasaGodwilTech/Ezee-money/main/images/submissions/SUB-1773074150582-bw0b0cb1h/agentPhoto_1773074157652.jpg"
      },
      "submissionDate": "2026-03-09T16:36:05.018Z",
      "status": "pending"
    },
    {
      "id": "SUB-1773482609876-oywyqlcyw",
      "submittedBy": {
        "agentName": "TIMOTHY KIBUKUNA",
        "agentScCode": "05544657",
        "agentId": "1772033414438"
      },
      "clientInfo": {
        "fullName": "Hirya joshua malwa",
        "phoneNumber": "0779672004",
        "email": "joshuamalwah@gmail.com",
        "nationalId": "CM890601013QTG",
        "dob": "1989-10-24",
        "gender": "male",
        "businessAddress": "Nauyo",
        "residentialAddress": "Mbale",
        "nextOfKinName": "Gloria mercy",
        "nextOfKinRelationship": "other_relative",
        "nextOfKinPhone": "705925375"
      },
      "images": {
        "idFrontUrl": "https://raw.githubusercontent.com/BarasaGodwilTech/Ezee-money/main/images/submissions/SUB-1773482609876-oywyqlcyw/idFront_1773482609926.jpg",
        "idBackUrl": "https://raw.githubusercontent.com/BarasaGodwilTech/Ezee-money/main/images/submissions/SUB-1773482609876-oywyqlcyw/idBack_1773482626639.jpg",
        "agentPhotoUrl": "https://raw.githubusercontent.com/BarasaGodwilTech/Ezee-money/main/images/submissions/SUB-1773482609876-oywyqlcyw/agentPhoto_1773482635861.jpg"
      },
      "submissionDate": "2026-03-14T10:04:07.401Z",
      "status": "pending"
    },
    {
      "id": "SUB-1773483739344-sgz193wyg",
      "submittedBy": {
        "agentName": "TIMOTHY KIBUKUNA",
        "agentScCode": "05544657",
        "agentId": "1772033414438"
      },
      "clientInfo": {
        "fullName": "NAMBUYA SHAMILAH",
        "phoneNumber": "0770590381",
        "email": "shamilahnambuya0@gmail.com",
        "nationalId": "CF04026109YCND",
        "dob": "2004-12-20",
        "gender": "female",
        "businessAddress": "Nauyo",
        "residentialAddress": "Mbale",
        "nextOfKinName": "Naluya",
        "nextOfKinRelationship": "friend",
        "nextOfKinPhone": "0705925374"
      },
      "images": {
        "idFrontUrl": "https://raw.githubusercontent.com/BarasaGodwilTech/Ezee-money/main/images/submissions/SUB-1773483739344-sgz193wyg/idFront_1773483739403.jpg",
        "idBackUrl": "https://raw.githubusercontent.com/BarasaGodwilTech/Ezee-money/main/images/submissions/SUB-1773483739344-sgz193wyg/idBack_1773483765994.jpg",
        "agentPhotoUrl": "https://raw.githubusercontent.com/BarasaGodwilTech/Ezee-money/main/images/submissions/SUB-1773483739344-sgz193wyg/agentPhoto_1773483783258.jpg"
      },
      "submissionDate": "2026-03-14T10:23:13.617Z",
      "status": "pending"
    },
    {
      "id": "SUB-1773499715066-ltkmquaei",
      "submittedBy": {
        "agentName": "TIMOTHY KIBUKUNA",
        "agentScCode": "05544657",
        "agentId": "1772033414438"
      },
      "clientInfo": {
        "fullName": "Shibuta  Aziz Abdallah",
        "phoneNumber": "0701955029",
        "email": "shibutaaziz@gmail.com",
        "nationalId": "CM92026104XE2G",
        "dob": "1992-11-26",
        "gender": "male",
        "businessAddress": "Nauyo",
        "residentialAddress": "Mbale",
        "nextOfKinName": "Naluya",
        "nextOfKinRelationship": "friend",
        "nextOfKinPhone": "0704325375"
      },
      "images": {
        "idFrontUrl": "https://raw.githubusercontent.com/BarasaGodwilTech/Ezee-money/main/images/submissions/SUB-1773499715066-ltkmquaei/idFront_1773499715098.jpg",
        "idBackUrl": "https://raw.githubusercontent.com/BarasaGodwilTech/Ezee-money/main/images/submissions/SUB-1773499715066-ltkmquaei/idBack_1773499731804.jpg",
        "agentPhotoUrl": "https://raw.githubusercontent.com/BarasaGodwilTech/Ezee-money/main/images/submissions/SUB-1773499715066-ltkmquaei/agentPhoto_1773499741035.jpg"
      },
      "submissionDate": "2026-03-14T14:49:09.269Z",
      "status": "pending"
    }
  ],
  "lastUpdated": "2026-03-14T14:49:09.947Z",
  "totalSubmissions": 8
}